dictionary/__init__.py
dictionary/lookalikes.py
dictionary/lowercase.py
dictionary/numbers.py
dictionary/prevent_misreadings.py
dictionary/uppercase.py
nanoid/__init__.py
nanoid/complex_generate.py
nanoid/non_secure_generate.py
test_nid-1.0.0.dist-info/LICENSE
test_nid-1.0.0.dist-info/METADATA
test_nid-1.0.0.dist-info/WHEEL
test_nid-1.0.0.dist-info/top_level.txt
test_nid-1.0.0.dist-info/RECORD
