Metadata-Version: 2.1
Name: test-nid
Version: 1.0.0
Summary: A tiny, secure, URL-friendly, unique string ID generator for Python.
Home-page: https://github.com/aidarkhanov/py-nanoid2
Author: Dair Aidarkhanov
Author-email: dairaidarkhanov@gmail.com
License: MIT
Platform: UNKNOWN
Requires-Dist: pytest
